{
  "$id": "MPBorderStyle.json",
  "title": "BorderStyle",
  "type": "object",
  "$mash": {
    "sources": [
      { "$ref": "abstract/MPStyle.json#" },
      { "$ref": "mixins/MPContainedDocument.json#" }
    ],
    "with": {
      "properties": {
        "doubleLines": {
          "type": "boolean"
        },
        "objectType": {
          "type": "string",
          "enum": [ "MPBorderStyle" ]
        },
        "pattern": {
          "type": "array",
          "items": {
            "type": "number"
          }
        }
      },
      "required": [
      ]
    }
  }
}
